nemo_library_etl/__init__.py
nemo_library_etl/_version.py
nemo_library_etl/adapter/__init__.py
nemo_library_etl/adapter/_utils/__init__.py
nemo_library_etl/adapter/_utils/argparse.py
nemo_library_etl/adapter/_utils/cloud_dirs.py
nemo_library_etl/adapter/_utils/config.py
nemo_library_etl/adapter/_utils/datatype_handler.py
nemo_library_etl/adapter/_utils/db_handler_local.py
nemo_library_etl/adapter/_utils/db_handler_source.py
nemo_library_etl/adapter/_utils/dbandfileutils.py
nemo_library_etl/adapter/_utils/enums.py
nemo_library_etl/adapter/_utils/file_handler.py
nemo_library_etl/adapter/_utils/recursive_json_flattener.py
nemo_library_etl/adapter/_utils/sentiment_analyzer.py
nemo_library_etl/adapter/gedys/__init__.py
nemo_library_etl/adapter/gedys/__main__.py
nemo_library_etl/adapter/gedys/config_models_gedys.py
nemo_library_etl/adapter/gedys/extract.py
nemo_library_etl/adapter/gedys/flow.py
nemo_library_etl/adapter/gedys/load.py
nemo_library_etl/adapter/gedys/transform.py
nemo_library_etl/adapter/gedys/config/default_config_gedys.json
nemo_library_etl/adapter/hubspotforecast/__init__.py
nemo_library_etl/adapter/hubspotforecast/__main__.py
nemo_library_etl/adapter/hubspotforecast/config_models_hubspotforecast.py
nemo_library_etl/adapter/hubspotforecast/enums.py
nemo_library_etl/adapter/hubspotforecast/extract.py
nemo_library_etl/adapter/hubspotforecast/flow.py
nemo_library_etl/adapter/hubspotforecast/load.py
nemo_library_etl/adapter/hubspotforecast/symbols.py
nemo_library_etl/adapter/hubspotforecast/transform.py
nemo_library_etl/adapter/hubspotforecast/config/default_config_hubspotforecast.json
nemo_library_etl/adapter/migman/__init__.py
nemo_library_etl/adapter/migman/__main__.py
nemo_library_etl/adapter/migman/config_models_migman.py
nemo_library_etl/adapter/migman/enums.py
nemo_library_etl/adapter/migman/extract_from_database.py
nemo_library_etl/adapter/migman/extract_from_file.py
nemo_library_etl/adapter/migman/flow.py
nemo_library_etl/adapter/migman/load.py
nemo_library_etl-0.1.45.dist-info/licenses/LICENSE
nemo_library_etl-0.1.45.dist-info/METADATA
nemo_library_etl-0.1.45.dist-info/WHEEL
nemo_library_etl-0.1.45.dist-info/top_level.txt
nemo_library_etl-0.1.45.dist-info/RECORD
