Metadata-Version: 2.4
Name: nemo_library_etl
Version: 0.1.45
Summary: ETL Tools for Nemo
Author: Gunnar Schug
Author-email: GunnarSchug81@gmail.com
Project-URL: Github, https://github.com/NEMOGunnar/etl
Project-URL: NEMO, https://enter.nemo-ai.com/nemo/
Classifier: Programming Language :: Python :: 3.13
License-File: LICENSE
Requires-Dist: nemo_library
Requires-Dist: platformdirs
Requires-Dist: pyodbc
Requires-Dist: pyarrow
Requires-Dist: prefect
Requires-Dist: duckdb
Requires-Dist: transformers
Requires-Dist: pandas
Requires-Dist: torch
Requires-Dist: rapidfuzz
Requires-Dist: sqlglot
Requires-Dist: hdbcli
Requires-Dist: nicegui
Dynamic: author
Dynamic: author-email
Dynamic: classifier
Dynamic: description
Dynamic: description-content-type
Dynamic: license-file
Dynamic: project-url
Dynamic: requires-dist
Dynamic: summary
